starlette/__init__.py
starlette/applications.py
starlette/authentication.py
starlette/background.py
starlette/concurrency.py
starlette/config.py
starlette/convertors.py
starlette/datastructures.py
starlette/endpoints.py
starlette/exceptions.py
starlette/formparsers.py
starlette/graphql.py
starlette/py.typed
starlette/requests.py
starlette/responses.py
starlette/routing.py
starlette/schemas.py
starlette/staticfiles.py
starlette/status.py
starlette/templating.py
starlette/testclient.py
starlette/types.py
starlette/websockets.py
starlette/middleware/__init__.py
starlette/middleware/authentication.py
starlette/middleware/base.py
starlette/middleware/cors.py
starlette/middleware/errors.py
starlette/middleware/gzip.py
starlette/middleware/httpsredirect.py
starlette/middleware/sessions.py
starlette/middleware/trustedhost.py
starlette/middleware/wsgi.py
starlette_naokipeter-0.12.0b3.data/data/LICENSE.md
starlette_naokipeter-0.12.0b3.dist-info/LICENSE.md
starlette_naokipeter-0.12.0b3.dist-info/METADATA
starlette_naokipeter-0.12.0b3.dist-info/WHEEL
starlette_naokipeter-0.12.0b3.dist-info/top_level.txt
starlette_naokipeter-0.12.0b3.dist-info/RECORD
