Metadata-Version: 2.1
Name: starlette-naokipeter
Version: 0.12.0b3
Summary: The little ASGI library that shines.
Home-page: https://github.com/naokipeter/starlette
Author: Tom Christie
Author-email: tom@tomchristie.com
License: BSD
Platform: UNKNOWN
Classifier: Development Status :: 3 - Alpha
Classifier: Environment :: Web Environment
Classifier: Intended Audience :: Developers
Classifier: License :: OSI Approved :: BSD License
Classifier: Operating System :: OS Independent
Classifier: Topic :: Internet :: WWW/HTTP
Classifier: Programming Language :: Python :: 3
Classifier: Programming Language :: Python :: 3.6
Classifier: Programming Language :: Python :: 3.7
Requires-Python: >=3.6
Provides-Extra: full
Requires-Dist: aiofiles ; extra == 'full'
Requires-Dist: asyncpg ; extra == 'full'
Requires-Dist: graphene ; extra == 'full'
Requires-Dist: itsdangerous ; extra == 'full'
Requires-Dist: jinja2 ; extra == 'full'
Requires-Dist: python-multipart ; extra == 'full'
Requires-Dist: pyyaml ; extra == 'full'
Requires-Dist: requests ; extra == 'full'
Requires-Dist: ujson ; extra == 'full'
